metaquant/__init__.py
metaquant/__main__.py
metaquant/cog.py
metaquant/definitions.py
metaquant/function_taxonomy_interaction.py
metaquant/functional_analysis.py
metaquant/go.py
metaquant/io.py
metaquant/main.py
metaquant/parser.py
metaquant/phylo_tree.py
metaquant/runner.py
metaquant/stats.py
metaquant/taxonomy_analysis.py
metaquant/utils.py
metaquant/data/__init__.py
metaquant/data/go-basic.obo
metaquant/data/goslim_generic.obo
metaquant-0.1.2.dist-info/METADATA
metaquant-0.1.2.dist-info/RECORD
metaquant-0.1.2.dist-info/WHEEL
metaquant-0.1.2.dist-info/entry_points.txt
metaquant-0.1.2.dist-info/top_level.txt
src/__init__.py
src/cog.py
src/function_taxonomy_interaction.py
src/functional_analysis.py
src/go.py
src/io.py
src/parser.py
src/phylo_tree.py
src/stats.py
src/taxonomy_analysis.py
src/utils.py
