Metadata-Version: 2.1
Name: metaquant
Version: 0.1.2
Summary: Quantitative microbiome analysis
Home-page: UNKNOWN
Author: Caleb Easterly
Author-email: easte080@umn.edu
License: Apache License 2.0
Project-URL: Bug Tracker, https://github.com/caleb-easterly/metaquant/issues
Project-URL: Source Code, https://github.com/caleb-easterly/metaquant
Platform: UNKNOWN
Classifier: Development Status :: 3 - Alpha
Classifier: License :: OSI Approved :: Apache Software License
Classifier: Operating System :: MacOS
Classifier: Operating System :: Unix
Classifier: Programming Language :: Python :: 3
Classifier: Topic :: Scientific/Engineering :: Bio-Informatics
Classifier: Intended Audience :: Science/Research
Requires-Python: >=3.5
Requires-Dist: pandas
Requires-Dist: ete3
Requires-Dist: goatools
Requires-Dist: wget
Requires-Dist: numpy
Requires-Dist: statsmodels
